{
  "id": "16101",
  "name": "Memory",
  "slug": "memory",
  "description": "Are you a genius? Are you ready to challenge your memory? We are very happy to introduce you the best memory game to train your brain while having fun! \"Genius Memory\" is a fun memory game for all the family !... Recommended only for families with brain",
  "instructions": "Are you a genius Are you ready to challenge your memory We are very happy to introduce you the best memory game to train your brain while having fun Genius Memory is a fun memory game for all the family Recommended only for families with brain",
  "category": "Puzzle",
  "tags": [
    "Ben 10",
    "Brain",
    "Casual",
    "Fun",
    "Funny",
    "Girl",
    "Girls",
    "Hypercasual",
    "Kid",
    "Kids",
    "Math",
    "Memory",
    "Puzzle"
  ],
  "url": "https://html5.gamemonetize.co/feq5hkgxjhww8p1a98xiev9wpxqyixyy/",
  "embedUrl": "https://html5.gamemonetize.co/feq5hkgxjhww8p1a98xiev9wpxqyixyy/",
  "image": "https://img.gamemonetize.com/feq5hkgxjhww8p1a98xiev9wpxqyixyy/512x384.jpg",
  "width": "800",
  "height": "600",
  "rating": "4.8"
}