{
  "id": "67217",
  "name": "Royal King: Croos  Avatar Run",
  "slug": "royal-king-croos-avatar-run",
  "description": "Royal King: Croos- Avatar Run is a fast and fun royal adventure where you control your life_run_avatar through a puzzle_kingdom of quick decisions and perfect timing! Gameplay Tap to grow the stick and cross between platforms. Hit the perfect timing for bonus rewards. Speed increases, platforms get tougher&mdash;stay alive and beat your best score! Highlights Glorious challenges that keep getting harder Castles design with a true kingdom vibe A Charming story atmosphere Beautiful graphics and smooth gameplay Easy to play, hard to master Download now and prove you&rsquo;re the king of the run!",
  "instructions": "Tap to grow the stick and cross between platforms Hit the perfect timing for bonus rewards Speed increases platforms get tougher mdash stay alive and beat your best score ",
  "category": "Girls",
  "tags": [
    "2D",
    "Baby Games",
    "Barbie",
    "beauty",
    "Dress Up",
    "WebGL"
  ],
  "url": "https://html5.gamemonetize.co/28ktdsst1s1kdhqlm38ajj63wjllib7a/",
  "embedUrl": "https://html5.gamemonetize.co/28ktdsst1s1kdhqlm38ajj63wjllib7a/",
  "image": "https://img.gamemonetize.com/28ktdsst1s1kdhqlm38ajj63wjllib7a/512x384.jpg",
  "width": "800",
  "height": "600",
  "rating": "4.7"
}