{
  "id": "73563",
  "name": "Pocket Stress Relief Games",
  "slug": "pocket-stress-relief-games",
  "description": "Need to unwind after a long day? Step into a world of calm with antistress relaxing fidget toys. This popit game is designed to help you relax, focus, and find peace. Explore an array of soothing pop it toys and stress-relief games that stimulate the satisfying experience of puppet games and mindful exercises. Engage with various relaxation toys, each with unique interactions and calming sounds.",
  "instructions": "Left Mouse Click",
  "category": "Puzzle",
  "tags": [
    "2025 games",
    "2026 games",
    "3D Games",
    "Best Games",
    "Fun",
    "Games",
    "html5 games",
    "Kids",
    "Relaxation"
  ],
  "url": "https://html5.gamemonetize.co/zf9ivma2rjjgz3n6l71jaq8dou42ibpi/",
  "embedUrl": "https://html5.gamemonetize.co/zf9ivma2rjjgz3n6l71jaq8dou42ibpi/",
  "image": "https://img.gamemonetize.com/zf9ivma2rjjgz3n6l71jaq8dou42ibpi/512x384.jpg",
  "width": "800",
  "height": "600",
  "rating": "4.6"
}