{
  "id": "73561",
  "name": "Stress Relief Mini Games",
  "slug": "stress-relief-mini-games",
  "description": "Antistress Relaxing toys &amp; Stress Relief is a calm game with stress relief games, satisfying and relaxing games, anxiety relief games, pop it games. Relax your mind and have something to do in boring moments! Have a break! With some amazing creativity, hundreds of designers took it upon themselves to make their own fun toys.",
  "instructions": "Left Mouse Click",
  "category": "Puzzle",
  "tags": [
    "2026 games",
    "3D Games",
    "Arcade",
    "Brainrot",
    "free html5 games for your website",
    "Game",
    "puzzleblock",
    "Relaxation",
    "unity games"
  ],
  "url": "https://html5.gamemonetize.co/o5g16n86iol1tfnm6xik4qhhboo19qmo/",
  "embedUrl": "https://html5.gamemonetize.co/o5g16n86iol1tfnm6xik4qhhboo19qmo/",
  "image": "https://img.gamemonetize.com/o5g16n86iol1tfnm6xik4qhhboo19qmo/512x384.jpg",
  "width": "800",
  "height": "600",
  "rating": "4.4"
}