{
  "id": "73747",
  "name": "Gothic Knife",
  "slug": "gothic-knife",
  "description": "Test your reflexes and precision in this addictive knife throwing game! Your goal is simple: throw knives into the rotating logs to break them. Be careful not to hit the knives youve already thrown! Key Features: &bull; Challenge yourself with endless levels. &bull; Battle unique Bosses every 3 stages! &bull; Explore 3 stunning themes: Cyberpunk, Gothic, and Village. &bull; Collect bonuses to earn extra knives. &bull; Master the Combo system for massive high scores!",
  "instructions": "Tap the screen or click the mouse to throw a knife ",
  "category": "Hypercasual",
  "tags": [
    "1 Player",
    "Mobile",
    "Pixel"
  ],
  "url": "https://html5.gamemonetize.co/eug6wzijzbk3ykimgaogrpbt4d05rnt8/",
  "embedUrl": "https://html5.gamemonetize.co/eug6wzijzbk3ykimgaogrpbt4d05rnt8/",
  "image": "https://img.gamemonetize.com/eug6wzijzbk3ykimgaogrpbt4d05rnt8/512x384.jpg",
  "width": "720",
  "height": "1280",
  "rating": "4.3"
}