{
  "id": "73908",
  "name": "Wolf Simulator Forest Hunt 3D",
  "slug": "wolf-simulator-forest-hunt-3d",
  "description": "Explore nature as a wild animal and raise a family in the wilderness in Wildcraft, a new RPG adventure set in a huge 3D landscape! Start your adventure as a wolf, fox, lynx and more, and take your family on a new adventure. Play with friends in multiplayer games and form animal families to protect your cubs from enemies. Unlock new animal breeds as your family legacy grows in Wildcraft! Online Multiplayer Simulator Compete with players from all around the World! The wilderness is never empty. Meet other wolves in real time and conquer the forest!",
  "instructions": "use mouse LMB hit WASD E eat F drink P pick Space Jump ESC pause menu TAB Objective",
  "category": "Adventure",
  "tags": [
    "2025 games",
    "3D Games",
    "Action",
    "Animal",
    "Arcade",
    "Forest",
    "Game",
    "Hunting",
    "Simulator",
    "Wolf"
  ],
  "url": "https://html5.gamemonetize.co/obte6bemd7au25zgt9xva9wlnzerhzm2/",
  "embedUrl": "https://html5.gamemonetize.co/obte6bemd7au25zgt9xva9wlnzerhzm2/",
  "image": "https://img.gamemonetize.com/obte6bemd7au25zgt9xva9wlnzerhzm2/512x384.jpg",
  "width": "800",
  "height": "600",
  "rating": "5.0"
}