{
  "id": "74360",
  "name": "Knee Case Simulator",
  "slug": "knee-case-simulator",
  "description": "Oops, Tiara fell and hurt her knee! Dont worry, youre here to save the day! Jump in as a doctor and fix her up with some quick knee surgery. Follow the right steps to ensure shes back on her feet in no time. Once shes healed, its time for some fun! Check out some cute outfits and accessories in our collection and give her a fresh, stunning look!",
  "instructions": "Use MOUSE to play the game ",
  "category": "Hypercasual",
  "tags": [
    "Doctor",
    "Dress Up",
    "Simulation",
    "Surgery"
  ],
  "url": "https://html5.gamemonetize.co/34bokq1kfeghn5db0gklnun2xhfszzn8/",
  "embedUrl": "https://html5.gamemonetize.co/34bokq1kfeghn5db0gklnun2xhfszzn8/",
  "image": "https://img.gamemonetize.com/34bokq1kfeghn5db0gklnun2xhfszzn8/512x384.jpg",
  "width": "800",
  "height": "600",
  "rating": "4.0"
}