{
  "id": "74825",
  "name": "Endless Ball Ride Game",
  "slug": "endless-ball-ride-game",
  "description": "Endless Ball: Downhill Ride Bring your skills to the next level by exploring and extending this complete 3D endless runner game! Endless Ball: Downhill Ride is a simple but challeging endless runner game, ready to be extended by you! The game comes with a complete and animated UI, an endless game experience with increasing level of difficulty, as well as an integrated score and highscore system.",
  "instructions": "W Arrow Up rarr Move Front S Arrow Down rarr Move Back A Arrow Left rarr Move Left D Arrow Right rarr Move Right - To click any button use mouse",
  "category": "Puzzle",
  "tags": [
    "amazing",
    "Ball",
    "Casual",
    "Hypercasual",
    "Top Down"
  ],
  "url": "https://html5.gamemonetize.co/wnfswonlbf082z66f9keryvrl35gkng2/",
  "embedUrl": "https://html5.gamemonetize.co/wnfswonlbf082z66f9keryvrl35gkng2/",
  "image": "https://img.gamemonetize.com/wnfswonlbf082z66f9keryvrl35gkng2/512x384.jpg",
  "width": "800",
  "height": "600",
  "rating": "4.3"
}