{
  "id": "75062",
  "name": "Block 21",
  "slug": "block-21",
  "description": "Tap/click on a group of three or more blocks with the same color. Get block 21. Have fun!",
  "instructions": "Tap the screen or click the mouse ",
  "category": "Puzzle",
  "tags": [
    "Block",
    "Brain",
    "HTML5",
    "Logic",
    "Puzzle"
  ],
  "url": "https://html5.gamemonetize.co/7y7eipr5axagurxl3zy7urjidst7c413/",
  "embedUrl": "https://html5.gamemonetize.co/7y7eipr5axagurxl3zy7urjidst7c413/",
  "image": "https://img.gamemonetize.com/7y7eipr5axagurxl3zy7urjidst7c413/512x384.jpg",
  "width": "1280",
  "height": "720",
  "rating": "4.9"
}