{
  "id": "75116",
  "name": "Vice City Mad Driving",
  "slug": "vice-city-mad-driving",
  "description": "Vice City Mad Driving is an open city driving game where chaos meets freedom. Explore a neon city inspired by classic vice streets, drive fast cars, perform crazy stunts, smash through traffic, and cause mayhem with no rules holding you back. Jump into free roam driving, test your skills, and enjoy pure arcade madness directly in your browser.",
  "instructions": "WASD - Drive Space - Brake R - Restart Mouse - Rotate view TAB - Pause ",
  "category": "Racing",
  "tags": [
    "1 Player",
    "3D",
    "3D Games",
    "Car",
    "Cars",
    "Driving",
    "gta",
    "Race",
    "Racing",
    "Supercars",
    "Unity3D"
  ],
  "url": "https://html5.gamemonetize.co/sjq4qrvuzt2vrxwh89cxxc02hhb9arst/",
  "embedUrl": "https://html5.gamemonetize.co/sjq4qrvuzt2vrxwh89cxxc02hhb9arst/",
  "image": "https://img.gamemonetize.com/sjq4qrvuzt2vrxwh89cxxc02hhb9arst/512x384.jpg",
  "width": "960",
  "height": "600",
  "rating": "4.8"
}