{
  "id": "75140",
  "name": "Build a tower",
  "slug": "build-a-tower",
  "description": "Tap to build your dream skyscraper! Every click adds a new floor. Challenge friends on the global leaderboard and unlock unique designs to customize your tower. How high can you go? Simple, addictive, and endlessly fun. Start building your empire in the sky now!",
  "instructions": "Tap to stack floors and compete for the highest tower ",
  "category": "Puzzle",
  "tags": [
    "build",
    "Tower Defense"
  ],
  "url": "https://html5.gamemonetize.co/almujssv4w7v7lhnc2jjrd37os40dh75/",
  "embedUrl": "https://html5.gamemonetize.co/almujssv4w7v7lhnc2jjrd37os40dh75/",
  "image": "https://img.gamemonetize.com/almujssv4w7v7lhnc2jjrd37os40dh75/512x384.jpg",
  "width": "800",
  "height": "600",
  "rating": "5.0"
}