{
  "id": "75751",
  "name": "Save The Princess 1",
  "slug": "save-the-princess-1",
  "description": "Save the Princess 1: The Legend of the Pure Heart A night of peace. A promise whispered beneath the stars. At dawn&hellip; she is gone. The Cat Prince knows it was not chance that took her away, but a shadow bold enough to shatter what was pure. She is more than a princess. She is kindness, quiet strength, a light that gives meaning to the world itself. Without powers. Without certainty. He begins his journey. Armed only with love. Guided only by courage. He crosses hostile lands, faces monsters and fear, helped by a brilliant friend who can open paths where hope was never meant to exist. Someone desires her. Someone wants",
  "instructions": " larr rarr ndash Move left right uarr ndash Jump",
  "category": "Adventure",
  "tags": [
    "1 Player",
    "Action",
    "Castle",
    "Enemies",
    "Escape",
    "Fairy",
    "Fantasy",
    "Forest",
    "jump",
    "Levels",
    "Magic",
    "Monster",
    "Obstacle",
    "run"
  ],
  "url": "https://html5.gamemonetize.co/4jo9jz2oskhkhnzejg5iaoc1k90jlkyp/",
  "embedUrl": "https://html5.gamemonetize.co/4jo9jz2oskhkhnzejg5iaoc1k90jlkyp/",
  "image": "https://img.gamemonetize.com/4jo9jz2oskhkhnzejg5iaoc1k90jlkyp/512x384.jpg",
  "width": "800",
  "height": "600",
  "rating": "4.5"
}