{
  "id": "75928",
  "name": "Mr. Bean 3D Jigsaw",
  "slug": "mr-bean-3d-jigsaw",
  "description": "In the game Mr.Bean 3D Jigsaw you will find a cute set of puzzles. All the pictures are dedicated to the popular character Mr.Bean and the set has its own peculiarity. You will be presented with scattered volumetric fragments at each level. Move and move them to connect them. If the fragments fit together, their connection will become unbreakable. The end result will be a whole picture that will appear before you as soon as the last fragment is connected. Gradually, the number of pieces will increase and reach a maximum number of 96.",
  "instructions": "Mouse click or tap to play",
  "category": "Puzzle",
  "tags": [
    "1 Player",
    "Android",
    "Best",
    "Cartoon",
    "Fun",
    "Funny",
    "Jigsaw",
    "Kids",
    "Mobile",
    "Skill"
  ],
  "url": "https://html5.gamemonetize.co/ildo8xjr8mymzcsuotmow174qgqjtgwt/",
  "embedUrl": "https://html5.gamemonetize.co/ildo8xjr8mymzcsuotmow174qgqjtgwt/",
  "image": "https://img.gamemonetize.com/ildo8xjr8mymzcsuotmow174qgqjtgwt/512x384.jpg",
  "width": "1280",
  "height": "720",
  "rating": "4.6"
}