{
  "id": "76023",
  "name": "Bank Robbery Sneak Master",
  "slug": "bank-robbery-sneak-master",
  "description": "Bank Robbery Sneak Master is a fun, humor-packed stealth adventure where you play as a sneaky burglar with a good heart. Take on final jobs before leaving the criminal life behind! Sneak past security guards, residents, and sleeping dogs using ninja skills and puzzle solving tactics. Explore luxurious villas, Downtown streets, secret labs, and challenging maps filled with loot. Steal secret documents, TV remotes, and hidden treasures without getting detected. Enjoy hilarious animations, a twisting storyline, and rewarding puzzles.",
  "instructions": "WASD ndash Move Shift ndash Sprint F ndash Shoot Z ndash Zoom",
  "category": "Arcade",
  "tags": [
    "2026 games",
    "3D Games",
    "Avoid",
    "Escape",
    "Hypercasual",
    "run",
    "Shooting",
    "Skill",
    "sneak",
    "Stealth",
    "Strategy",
    "Thief"
  ],
  "url": "https://html5.gamemonetize.co/5vvmlf18g39d0ukqod1inayzg03154hl/",
  "embedUrl": "https://html5.gamemonetize.co/5vvmlf18g39d0ukqod1inayzg03154hl/",
  "image": "https://img.gamemonetize.com/5vvmlf18g39d0ukqod1inayzg03154hl/512x384.jpg",
  "width": "800",
  "height": "600",
  "rating": "4.2"
}