{
  "id": "76135",
  "name": "berry bury berry",
  "slug": "berry-bury-berry",
  "description": "Berry Bury Berry is a colorful and addictive 3D arcade game where speed and precision are the key to survival! Dive into a vibrant world full of obstacles, challenges, and fast-paced action. Control your character, collect berries, avoid dangerous traps, and reach the finish line without crashing. With smooth controls, satisfying gameplay mechanics, and eye-catching 3D graphics, Berry Bury Berry delivers a fun and engaging hypercasual experience for players of all ages. Test your reflexes, improve your timing, and challenge yourself in this exciting arcade adventure! Perfect for fans of casual 3D skill games and fast reaction challenges.",
  "instructions": "right click to pickup left click to throw AWSD to move and Q to drop",
  "category": "Arcade",
  "tags": [
    "3D",
    "3D Games",
    "Arcade",
    "Casual",
    "Collecting",
    "Color",
    "Funny",
    "HTML",
    "Hypercasual",
    "Kids",
    "Skills"
  ],
  "url": "https://html5.gamemonetize.co/4z94mtbvcosric14qrb6d7tcg4bw5o32/",
  "embedUrl": "https://html5.gamemonetize.co/4z94mtbvcosric14qrb6d7tcg4bw5o32/",
  "image": "https://img.gamemonetize.com/4z94mtbvcosric14qrb6d7tcg4bw5o32/512x384.jpg",
  "width": "800",
  "height": "600",
  "rating": "4.4"
}