{
  "id": "76194",
  "name": "Rotate Ring Game",
  "slug": "rotate-ring-game",
  "description": "Welcome to Off The Ring Game, an exciting and addictive arcade challenge where your timing, focus, and precision skills are put to the test. Your goal is simple: guide the moving object safely through the ring path without touching the edges. Sounds easy &mdash; but mastering the timing requires skill and concentration. This fast-paced arcade game offers smooth gameplay, satisfying mechanics, and progressively challenging levels that keep players engaged. Whether you enjoy reaction-based games or relaxing skill challenges, Off The Ring Game delivers endless fun.",
  "instructions": "- To click any button use mouse ",
  "category": "Puzzle",
  "tags": [
    "2026 games",
    "amazing",
    "Casual",
    "Fun",
    "Pinball"
  ],
  "url": "https://html5.gamemonetize.co/iau5yh64pq69lpvp2nhgm4jshulheqkk/",
  "embedUrl": "https://html5.gamemonetize.co/iau5yh64pq69lpvp2nhgm4jshulheqkk/",
  "image": "https://img.gamemonetize.com/iau5yh64pq69lpvp2nhgm4jshulheqkk/512x384.jpg",
  "width": "800",
  "height": "600",
  "rating": "4.8"
}