{
  "id": "76213",
  "name": "Bottle Storm: Elite Beach",
  "slug": "bottle-storm-elite-beach",
  "description": "Step into the ultimate tactical shooting range in Bottle Storm: Elite Beach! Aim carefully, break bottles, and avoid dangerous red bottles as you climb levels. Unlock new weapons, improve your reflexes, and master the beach arena. Can you reach the highest score without missing too many targets? Test your skill in this fast-paced, addictive arcade shooter!",
  "instructions": "Desktop Mouse Aim and shoot bottles Left Click Shoot Mobile Touch Tap Touch Shoot at bottles Drag finger Move crosshair optional auto-follow ",
  "category": "Shooting",
  "tags": [
    "Shooting"
  ],
  "url": "https://html5.gamemonetize.co/slfq5wm1etragwl0400yld5cccha3om1/",
  "embedUrl": "https://html5.gamemonetize.co/slfq5wm1etragwl0400yld5cccha3om1/",
  "image": "https://img.gamemonetize.com/slfq5wm1etragwl0400yld5cccha3om1/512x384.jpg",
  "width": "800",
  "height": "600",
  "rating": "4.5"
}