{
  "id": "76303",
  "name": "Miner Rush Game",
  "slug": "miner-rush-game",
  "description": "Miner Rush is an exciting endless runner adventure that takes you deep into underground tunnels filled with gold, gems, and hidden treasures. Step into the boots of a brave miner and race through dangerous caves, narrow tracks, and rocky pathways while collecting valuable resources. Dodge obstacles, avoid collapsing tunnels, and keep moving forward to achieve the highest score in this fast-paced mining adventure.",
  "instructions": "- To click any button use mouse ",
  "category": "Hypercasual",
  "tags": [
    "2026 games",
    "amazing",
    "Casual",
    "Funny",
    "Hypercasual"
  ],
  "url": "https://html5.gamemonetize.co/catxgyk1e4g6yk44beq404rfz6c6jnko/",
  "embedUrl": "https://html5.gamemonetize.co/catxgyk1e4g6yk44beq404rfz6c6jnko/",
  "image": "https://img.gamemonetize.com/catxgyk1e4g6yk44beq404rfz6c6jnko/512x384.jpg",
  "width": "800",
  "height": "600",
  "rating": "4.7"
}