{
  "id": "77230",
  "name": "HogHavoc",
  "slug": "hoghavoc",
  "description": "This is a game about rising up vertically and avoiding collision with moviing animals. You also have limited bullets to shoot them up. The higher you climb, the more you score.",
  "instructions": "Avoid animals ",
  "category": "Hypercasual",
  "tags": [
    "Animal",
    "Army",
    "Casino",
    "Casual"
  ],
  "url": "https://html5.gamemonetize.co/jky2ccbui6itaxvfia0tms9bo0zorn48/",
  "embedUrl": "https://html5.gamemonetize.co/jky2ccbui6itaxvfia0tms9bo0zorn48/",
  "image": "https://img.gamemonetize.com/jky2ccbui6itaxvfia0tms9bo0zorn48/512x384.jpg",
  "width": "800",
  "height": "600",
  "rating": "5.0"
}