{
  "id": "78219",
  "name": "Tapping on Fruit",
  "slug": "tapping-on-fruit",
  "description": "*Knock the Fruit* is a casual mini-game belonging to the match-and-eliminate genre. The gameplay mechanics are as follows: set within a 9x9 grid matrix, the core objective is to eliminate adjacent fruits of the same color to meet the target score required for each level. Players can eliminate adjacent fruits&mdash;either vertically and horizontally (in Normal Mode) or in all eight directions (in Hammer Mode)&mdash;simply by tapping on a fruit. Points are awarded for eliminating two or more fruits in a single move, with the score calculation dependent on both the quantity of fruits eliminated and the current level number. The game features two built-in",
  "instructions": "Mouse click or tap to play",
  "category": "Hypercasual",
  "tags": [
    "1 Player",
    "2D"
  ],
  "url": "https://html5.gamemonetize.co/imebx29rrsjqqz8uvcsazbc1cr51ttzw/",
  "embedUrl": "https://html5.gamemonetize.co/imebx29rrsjqqz8uvcsazbc1cr51ttzw/",
  "image": "https://img.gamemonetize.com/imebx29rrsjqqz8uvcsazbc1cr51ttzw/512x384.jpg",
  "width": "720",
  "height": "1280",
  "rating": "4.9"
}