{
  "id": "78604",
  "name": "Fill Line : one line puzzle game",
  "slug": "fill-line-one-line-puzzle-game",
  "description": "Looking for a way to sharpen your mind and relax at the same time? Welcome to Fill: One Line Puzzle Game, the minimalist brain teaser that&rsquo;s taking the world by storm. The rules are simple: connect all the squares on the grid using a single, unbroken line. It sounds easy, but as the grids grow and the paths become more complex, you&rsquo;ll need every bit of logic and spatial reasoning to find the solution. Why You&rsquo;ll Love Fill: Thousands of Levels: From beginner-friendly 4x4 grids to expert-level challenges. Daily Brain Training Minimalist Design No Time Pressure Stuck? No Problem",
  "instructions": "Start at the designated block Drag your finger to fill all the remaining blocks The Catch You cannot overlap lines or revisit a block you rsquo ve already filled ",
  "category": "Puzzle",
  "tags": [
    ".io Games",
    "2D",
    "Adventure",
    "Casual",
    "Hypercasual",
    "Puzzle"
  ],
  "url": "https://html5.gamemonetize.co/2x307mdmfkmohpv25ukcq2eqjwlnpesy/",
  "embedUrl": "https://html5.gamemonetize.co/2x307mdmfkmohpv25ukcq2eqjwlnpesy/",
  "image": "https://img.gamemonetize.com/2x307mdmfkmohpv25ukcq2eqjwlnpesy/512x384.jpg",
  "width": "350",
  "height": "600",
  "rating": "4.9"
}