{
  "id": "78868",
  "name": "Rescue Rush: Wildfire",
  "slug": "rescue-rush-wildfire",
  "description": "Rescue Rush: Wildfire is a fast-paced survival game where every second counts. A lightning strike ignites a wildfire, and it&rsquo;s up to you to save as many animals as possible before the flames spread out of control. Navigate the terrain, avoid hazards, and rescue animals while the fire grows more intense over time. Use water to protect yourself and extinguish flames, but stay alert&mdash;trees burn, paths change, and danger is always moving. Simple controls make it easy to jump in, while increasing pressure keeps every run challenging and rewarding. How long can you survive&mdash;and how many animals can you save?",
  "instructions": "Controls Move using bull W A S D bull Arrow Keys bull Controller Joystick Use the hose button or assigned control to spray water Water can extinguish fire and briefly protect you from flames On mobile bull Use the left joystick to mo",
  "category": "Arcade",
  "tags": [
    "1 Player",
    "2D",
    "Action",
    "Animal",
    "Arcade",
    "Fire",
    "firefighters",
    "Rescue",
    "survival"
  ],
  "url": "https://html5.gamemonetize.co/8vzcpkdpcj5bbrff3jsl6v0z4j1zmccn/",
  "embedUrl": "https://html5.gamemonetize.co/8vzcpkdpcj5bbrff3jsl6v0z4j1zmccn/",
  "image": "https://img.gamemonetize.com/8vzcpkdpcj5bbrff3jsl6v0z4j1zmccn/512x384.jpg",
  "width": "1280",
  "height": "720",
  "rating": "4.9"
}