{
  "id": "79312",
  "name": "Kick a Lucky Block: Tsunami Football",
  "slug": "kick-a-lucky-block-tsunami-football",
  "description": "Kick a Lucky Block: Tsunami Football is a fun and fast-paced game where your goal is simple &mdash; kick the lucky block as far as possible! Every kick gives you a chance to roll a unique brainrot and test your luck. Once you land, you turn into a brainrot and must escape a massive tsunami that you triggered yourself! The farther you kick, the bigger the rewards &mdash; but also the greater the danger. Collect brainrots and place them on your plot to generate income. Buy weights and train your legs to kick farther and stronger! The game blends randomness, progression, and action into an exciting gameplay loop perfect for quick sessions.",
  "instructions": "Kick the Lucky Block as far as you can When you land youll transform into a Brainrot Your goal is to escape the massive tsunami ",
  "category": "Arcade",
  "tags": [
    "Brainrot",
    "Brainrot Italian",
    "Brainrot sahuuur",
    "Craft",
    "Football",
    "Italian Brainrot",
    "Minecraft",
    "roblox",
    "run",
    "running",
    "steal"
  ],
  "url": "https://html5.gamemonetize.co/w0niw3a0zkklmu5tblmf8t78me8hrk8g/",
  "embedUrl": "https://html5.gamemonetize.co/w0niw3a0zkklmu5tblmf8t78me8hrk8g/",
  "image": "https://img.gamemonetize.com/w0niw3a0zkklmu5tblmf8t78me8hrk8g/512x384.jpg",
  "width": "800",
  "height": "600",
  "rating": "4.2"
}