{
  "id": "79566",
  "name": "Stickman Sniper Shoot",
  "slug": "stickman-sniper-shoot",
  "description": "Step into the world of intense long-range combat in Stickman Sniper Shoot, an action-packed sniper shooting game where precision, patience, and fast reflexes are the keys to survival. Become an elite stickman sniper assassin and take on dangerous missions filled with enemies, secret operations, and high-risk targets. Every shot matters, and one mistake can mean mission failure.",
  "instructions": "- To click any button use mouse ",
  "category": "Puzzle",
  "tags": [
    "2026 games",
    "amazing",
    "Casual",
    "Fun",
    "Stickman"
  ],
  "url": "https://html5.gamemonetize.co/bymes51dz58zqon1ooz7db2ubsxyrz7g/",
  "embedUrl": "https://html5.gamemonetize.co/bymes51dz58zqon1ooz7db2ubsxyrz7g/",
  "image": "https://img.gamemonetize.com/bymes51dz58zqon1ooz7db2ubsxyrz7g/512x384.jpg",
  "width": "800",
  "height": "600",
  "rating": "4.3"
}