{
  "id": "80736",
  "name": "Duo Match 3D",
  "slug": "duo-match-3d",
  "description": "Two watermelons, two apples, two eggs; spot the pair and drag it into the hoop before the clock hits zero. Simple idea, but when the timer is ticking and the multiplier starts climbing you wont believe how fast your hands move. Match fast, stack up to x20 points and beat your own score. The more you chain, the bigger the reward. One rule: be quick. Great for a 2-minute break that turns into an hour.",
  "instructions": "Mouse click or tap to play",
  "category": "Puzzle",
  "tags": [
    "Brain",
    "mapi games",
    "Matching",
    "Puzzle"
  ],
  "url": "https://html5.gamemonetize.co/673vfpai43mknmn3imhsv0k149qydtn9/",
  "embedUrl": "https://html5.gamemonetize.co/673vfpai43mknmn3imhsv0k149qydtn9/",
  "image": "https://img.gamemonetize.com/673vfpai43mknmn3imhsv0k149qydtn9/512x384.jpg",
  "width": "800",
  "height": "600",
  "rating": "4.7"
}