{
  "id": "80969",
  "name": "Triad Tactics",
  "slug": "triad-tactics",
  "description": "Traid Tactics is a rock-paper-scissors game where you have to guess and click the winner. Enough time is given for kids to decide the winner, so it does not become too hectic to play the game. Have fun!",
  "instructions": "Click on the winner side ",
  "category": "Puzzle",
  "tags": [
    "Casual",
    "Puzzle"
  ],
  "url": "https://html5.gamemonetize.co/zl99s8urlkt2jb2k8gmb3fk41no35t7a/",
  "embedUrl": "https://html5.gamemonetize.co/zl99s8urlkt2jb2k8gmb3fk41no35t7a/",
  "image": "https://img.gamemonetize.com/zl99s8urlkt2jb2k8gmb3fk41no35t7a/512x384.jpg",
  "width": "800",
  "height": "600",
  "rating": "4.9"
}