{
  "id": "81110",
  "name": "Geometry Goal Dash 2026",
  "slug": "geometry-goal-dash-2026",
  "description": "Geometry Goal Dash 2026 is a fast-paced platformer inspired by Geometry Dash, where you control a rolling ball through challenging levels full of traps, jumps, and tight timing. Use arrow keys or WASD to guide your movement, avoid deadly obstacles, and survive intense levels that get harder the further you go. But there&rsquo;s a twist&hellip; Ronaldo is hunting you! Stay fast, stay precise, and don&rsquo;t let him catch you as you dash through chaotic football-themed worlds. Can you survive the ultimate mix of platforming skill and football madness?",
  "instructions": "WAD or Arrow keys to play ",
  "category": "Puzzle",
  "tags": [
    "Arcade",
    "Avoid",
    "Boys",
    "dash",
    "Geometry",
    "Hypercasual",
    "Jumping",
    "Platform",
    "Skill"
  ],
  "url": "https://html5.gamemonetize.co/7svc475rpf01zfyfzi1ej88u40td0jic/",
  "embedUrl": "https://html5.gamemonetize.co/7svc475rpf01zfyfzi1ej88u40td0jic/",
  "image": "https://img.gamemonetize.com/7svc475rpf01zfyfzi1ej88u40td0jic/512x384.jpg",
  "width": "854",
  "height": "480",
  "rating": "4.7"
}